Neel_Lib_SCA/__init__.py
Neel_Lib_SCA/core.py
neel_lib_sca-0.1.0.dist-info/METADATA
neel_lib_sca-0.1.0.dist-info/WHEEL
neel_lib_sca-0.1.0.dist-info/top_level.txt
neel_lib_sca-0.1.0.dist-info/RECORD
