Metadata-Version: 2.4
Name: Neel_Lib_SCA
Version: 0.1.0
Summary: Supply Chain analytics library for Django and Python projects.
Author-email: Neel Sawant <neel.sawant09@gmail.com>
Keywords: eoq,django,analysis,forecasting,products
Requires-Python: >=3.9
Requires-Dist: Django>=4.0
